markdgenerator/__about__.py
markdgenerator/__init__.py
markdgenerator/common.py
markdgenerator/config.py
markdgenerator/pandoc.py
markdgenerator-0.0.2.dist-info/LICENSE
markdgenerator-0.0.2.dist-info/METADATA
markdgenerator-0.0.2.dist-info/WHEEL
markdgenerator-0.0.2.dist-info/top_level.txt
markdgenerator-0.0.2.dist-info/RECORD
