Metadata-Version: 2.1
Name: markdgenerator
Version: 0.0.2
Summary: Package to generate text in pandoc markdown language
Home-page: https://github.com/petibear/markdgenerator
Author: Peter Marko
Author-email: peter.marko@outlook.com
License: BSD
Keywords: markdown,rst
Platform: UNKNOWN
Classifier: Programming Language :: Python :: 3
Classifier: License :: OSI Approved :: BSD License
Classifier: Development Status :: 3 - Alpha
Classifier: Intended Audience :: Developers
Classifier: Topic :: Utilities
Classifier: Topic :: Text Processing :: Markup
Requires-Python: >=3.6
Requires-Dist: pandas (>=0.24.0)
Provides-Extra: all
Requires-Dist: pytest ; extra == 'all'
Requires-Dist: sphinx ; extra == 'all'
Provides-Extra: doc
Requires-Dist: sphinx ; extra == 'doc'
Provides-Extra: test
Requires-Dist: pytest ; extra == 'test'
